zutil/ABL.py
zutil/__init__.py
zutil/algorithms.py
zutil/converters.py
zutil/farm.py
zutil/fileutils.py
zutil/kimchi.py
zutil/analysis/__init__.py
zutil/analysis/acoustic.py
zutil/analysis/data.py
zutil/analysis/get_case_dict.py
zutil/assets/ZCFD_Mark_CMYK.png
zutil/assets/ZCFD_NO_STRAPLINE_CMYK.png
zutil/assets/ZCFD_NO_STRAPLINE_WHITE.png
zutil/assets/ZCFD_STRAPLINE_CMYK.png
zutil/assets/ZCFD_STRAPLINE_WHITE.png
zutil/plot/__init__.py
zutil/plot/acoustic_plots.py
zutil/plot/colour.py
zutil/plot/font.py
zutil/plot/plot_report.py
zutil/plot/zplot.py
zutil/post/__init__.py
zutil/post/post.py
zutil/transform/__init__.py
zutil/transform/transform.py
zutil/zWind/ForceModels.py
zutil/zWind/__init__.py
zutil/zWind/transforms.py
zutil/zWind/zActuatorDisc.py
zutil/zWind/zBem.py
zutil/zWind/zController.py
zutil/zWind/zTurbine.py
zutil-2025.11.13331.12.dist-info/licenses/LICENSE
zutil-2025.11.13331.12.dist-info/METADATA
zutil-2025.11.13331.12.dist-info/WHEEL
zutil-2025.11.13331.12.dist-info/top_level.txt
zutil-2025.11.13331.12.dist-info/RECORD
